byte_codec/__init__.py
byte_codec/codec.py
byte_codec-0.1.4.dist-info/LICENSE
byte_codec-0.1.4.dist-info/METADATA
byte_codec-0.1.4.dist-info/WHEEL
byte_codec-0.1.4.dist-info/top_level.txt
byte_codec-0.1.4.dist-info/RECORD
