Metadata-Version: 2.1
Name: byte_codec
Version: 0.1.4
Summary: A simple Python library for encoding and decoding bytes
Author: Muhammad Daffa
Author-email: Muhammad Daffa <mdaffa2301@gmail.com>
License: MIT License
Project-URL: Homepage, https://github.com/dap23/byte_decoder
Keywords: bytes,decoder,utility
Classifier: License :: OSI Approved :: MIT License
Classifier: Programming Language :: Python
Classifier: Programming Language :: Python :: 3
Requires-Python: >=3.7
License-File: LICENSE
Provides-Extra: dev
Requires-Dist: pytest; extra == "dev"
